{
	"format_version": "1.21.0",
	"minecraft:geometry": [
		{
			"description": {
				"identifier": "geometry.trash_bin",
				"texture_width": 64,
				"texture_height": 64,
				"visible_bounds_width": 2,
				"visible_bounds_height": 2.5,
				"visible_bounds_offset": [0, 0.75, 0]
			},
			"bones": [
				{
					"name": "TrashBin",
					"pivot": [0, 0, 0],
					"cubes": [
						{
							"origin": [-6, 0, -6],
							"size": [12, 1, 12],
							"uv": {
								"north": {"uv": [0, 32], "uv_size": [12, 1]},
								"east": {"uv": [32, 12], "uv_size": [12, 1]},
								"south": {"uv": [32, 13], "uv_size": [12, 1]},
								"west": {"uv": [32, 14], "uv_size": [12, 1]},
								"up": {"uv": [16, 28], "uv_size": [12, 12]},
								"down": {"uv": [28, 40], "uv_size": [12, -12]}
							}
						},
						{
							"origin": [-7, 0, -7],
							"size": [14, 14, 1],
							"uv": {
								"north": {"uv": [16, 0], "uv_size": [14, 14]},
								"east": {"uv": [30, 12], "uv_size": [1, 14]},
								"south": {"uv": [16, 14], "uv_size": [14, 14]},
								"west": {"uv": [31, 12], "uv_size": [1, 14]},
								"up": {"uv": [30, 26], "uv_size": [14, 1]},
								"down": {"uv": [30, 28], "uv_size": [14, -1]}
							}
						},
						{
							"origin": [6, 0, -7],
							"size": [1, 14, 14],
							"uv": {
								"north": {"uv": [30, 12], "uv_size": [1, 14]},
								"east": {"uv": [16, 14], "uv_size": [14, 14]},
								"south": {"uv": [31, 12], "uv_size": [1, 14]},
								"west": {"uv": [16, 0], "uv_size": [14, 14]},
								"up": {"uv": [30, 26], "uv_size": [14, 1], "uv_rotation": 270},
								"down": {"uv": [30, 28], "uv_size": [14, -1], "uv_rotation": 90}
							}
						},
						{
							"origin": [-7, 0, -7],
							"size": [1, 14, 14],
							"uv": {
								"north": {"uv": [31, 12], "uv_size": [1, 14]},
								"east": {"uv": [16, 0], "uv_size": [14, 14]},
								"south": {"uv": [30, 12], "uv_size": [1, 14]},
								"west": {"uv": [16, 14], "uv_size": [14, 14]},
								"up": {"uv": [30, 26], "uv_size": [14, 1], "uv_rotation": 90},
								"down": {"uv": [30, 28], "uv_size": [14, -1], "uv_rotation": 270}
							}
						},
						{
							"origin": [-7, 0, 6],
							"size": [14, 14, 1],
							"uv": {
								"north": {"uv": [16, 14], "uv_size": [14, 14]},
								"east": {"uv": [31, 12], "uv_size": [1, 14]},
								"south": {"uv": [16, 0], "uv_size": [14, 14]},
								"west": {"uv": [30, 12], "uv_size": [1, 14]},
								"up": {"uv": [30, 26], "uv_size": [14, 1], "uv_rotation": 180},
								"down": {"uv": [30, 28], "uv_size": [14, -1], "uv_rotation": 180}
							}
						}
					]
				},
				{
					"name": "Lid",
					"parent": "TrashBin",
					"pivot": [0, 0, 0],
					"cubes": [
						{
							"origin": [-8, 13, -8],
							"size": [16, 3.01, 16],
							"uv": {
								"north": {"uv": [30, 0], "uv_size": [16, 3]},
								"east": {"uv": [30, 3], "uv_size": [16, 3]},
								"south": {"uv": [30, 6], "uv_size": [16, 3]},
								"west": {"uv": [30, 9], "uv_size": [16, 3]},
								"up": {"uv": [0, 0], "uv_size": [16, 16]},
								"down": {"uv": [0, 32], "uv_size": [16, -16]}
							}
						},
						{
							"origin": [-3, 17, -0.25],
							"size": [6, 1, 1],
							"uv": {
								"north": {"uv": [32, 15], "uv_size": [6, 1]},
								"east": {"uv": [12, 32], "uv_size": [1, 1]},
								"south": {"uv": [32, 16], "uv_size": [6, 1]},
								"west": {"uv": [13, 32], "uv_size": [1, 1]},
								"up": {"uv": [32, 17], "uv_size": [6, 1]},
								"down": {"uv": [32, 19], "uv_size": [6, -1]}
							}
						},
						{
							"origin": [2, 16, -0.25],
							"size": [1, 1, 1],
							"uv": {
								"north": {"uv": [14, 32], "uv_size": [1, 1]},
								"east": {"uv": [15, 32], "uv_size": [1, 1]},
								"south": {"uv": [32, 19], "uv_size": [1, 1]},
								"west": {"uv": [32, 20], "uv_size": [1, 1]},
								"up": {"uv": [32, 21], "uv_size": [1, 1]},
								"down": {"uv": [32, 23], "uv_size": [1, -1]}
							}
						},
						{
							"origin": [-3, 16, -0.25],
							"size": [1, 1, 1],
							"uv": {
								"north": {"uv": [32, 23], "uv_size": [1, 1]},
								"east": {"uv": [32, 24], "uv_size": [1, 1]},
								"south": {"uv": [32, 25], "uv_size": [1, 1]},
								"west": {"uv": [0, 33], "uv_size": [1, 1]},
								"up": {"uv": [1, 33], "uv_size": [1, 1]},
								"down": {"uv": [2, 34], "uv_size": [1, -1]}
							}
						}
					]
				}
			]
		}
	]
}